retux/__init__.py
retux/__main__.py
retux/const.py
retux/api/__init__.py
retux/api/error.py
retux/api/gateway.py
retux/api/http.py
retux/api/events/__init__.py
retux/api/events/abc.py
retux/api/events/connection.py
retux/api/events/guild.py
retux/api/events/message.py
retux/api/events/misc.py
retux/client/__init__.py
retux/client/bot.py
retux/client/flags.py
retux/client/mixins.py
retux/client/resources/__init__.py
retux/client/resources/abc.py
retux/client/resources/app_commands.py
retux/client/resources/application.py
retux/client/resources/channel.py
retux/client/resources/components.py
retux/client/resources/emoji.py
retux/client/resources/guild.py
retux/client/resources/guild_scheduled_event.py
retux/client/resources/guild_template.py
retux/client/resources/invite.py
retux/client/resources/role.py
retux/client/resources/sticker.py
retux/client/resources/user.py
retux/client/resources/voice_state.py
retux/client/resources/webhook.py
retux/utils/__init__.py
retux/utils/converters.py
retux-0.0.3.dist-info/LICENSE
retux-0.0.3.dist-info/METADATA
retux-0.0.3.dist-info/WHEEL
retux-0.0.3.dist-info/top_level.txt
retux-0.0.3.dist-info/RECORD
