Metadata-Version: 2.1
Name: retux
Version: 0.0.3
Summary: A Discord API wrapper built with good intentions.
Home-page: https://github.com/i0bs/retux
Author: i0
Author-email: me@i0.gg
Maintainer: i0
Maintainer-email: me@i0.gg
License: AGPL-3.0
Keywords: python discord discord-bot discord-api python3 discord-bots
Classifier: Intended Audience :: Developers
Classifier: Natural Language :: English
Classifier: Operating System :: OS Independent
Classifier: Programming Language :: Python :: 3
Classifier: Programming Language :: Python :: 3.10
Classifier: Topic :: Internet
Classifier: Topic :: Utilities
Classifier: Topic :: Software Development :: Libraries
Classifier: Topic :: Software Development :: Libraries :: Python Modules
Requires-Python: >=3.10.0
License-File: LICENSE
Requires-Dist: attrs
Requires-Dist: cattrs
Requires-Dist: httpx
Requires-Dist: trio
Requires-Dist: trio-websocket
